[
    {
        "name": "Microsoft Corporation",
        "ticker": "MSFT",
        "kurs": "384.36 USD",
        "perfTag": 0.26607946559607554,
        "perfMonat": -4.722247375526886,
        "perfJahr": -23.05414730960638,
        "perf5J": 44.418560491394544,
        "dividende": 0.009262150420636986,
        "kgv": 28.038269443931952,
        "kgv5J": 33.85688382654752,
        "kcv": 20.969088688580356,
        "kcv5J": 26.402441282924244,
        "watchlist": false,
        "tags": [
            "Tech",
            "MegaCap",
            "US"
        ],
        "logoUrl": "https://logo.clearbit.com/msft.com",
        "monate": "-",
        "frequenz": "-",
        "exDate": "-"
    },
    {
        "name": "Apple Inc.",
        "ticker": "AAPL",
        "kurs": "316.22 USD",
        "perfTag": 0.9030238488741635,
        "perfMonat": 8.834973156503978,
        "perfJahr": 50.36209444493459,
        "perf5J": 124.50573094382503,
        "dividende": 0.0033204730755381955,
        "kgv": 41.464473995615585,
        "kgv5J": 29.096640305469627,
        "kcv": 41.660857647413046,
        "kcv5J": 25.53393407259231,
        "watchlist": false,
        "tags": [
            "Tech",
            "Hardware",
            "US"
        ],
        "logoUrl": "https://logo.clearbit.com/aapl.com",
        "monate": "-",
        "frequenz": "-",
        "exDate": "-"
    },
    {
        "name": "Realty Income Corporation",
        "ticker": "O",
        "kurs": "63.17 USD",
        "perfTag": -0.09489383793358397,
        "perfMonat": 3.579967494190387,
        "perfJahr": 17.132977215791204,
        "perf5J": 21.558347674499522,
        "dividende": 0.05132183147020864,
        "kgv": 55.64529365727542,
        "kgv5J": 53.142499680328925,
        "kcv": 14.745726873958994,
        "kcv5J": 15.219024764010975,
        "watchlist": true,
        "tags": [
            "REIT",
            "Immobilien",
            "Monatszahler"
        ],
        "logoUrl": "https://logo.clearbit.com/o.com",
        "monate": "-",
        "frequenz": "-",
        "exDate": "-"
    },
    {
        "name": "Nestlé S.A.",
        "ticker": "NSRGY",
        "kurs": "103.06 USD",
        "perfTag": -0.41549938549792803,
        "perfMonat": 5.800219365644183,
        "perfJahr": 9.256930772108905,
        "perf5J": -4.784715571027523,
        "dividende": 0.03887056175915809,
        "kgv": 29.347170034336987,
        "kgv5J": 24.302171091562347,
        "kcv": 16.668321612183476,
        "kcv5J": 16.527428894154802,
        "watchlist": false,
        "tags": [
            "Konsum",
            "Dividende",
            "CH"
        ],
        "logoUrl": "https://logo.clearbit.com/nsrgy.com",
        "monate": "-",
        "frequenz": "-",
        "exDate": "-"
    }
]