[
    {"symbol": "MSFT", "name": "Microsoft", "logoUrl": "https://logo.clearbit.com/microsoft.com", "tags": ["Software", "Cloud", "KI"], "watchlist": false},
    {"symbol": "TSM", "name": "TSMC", "logoUrl": "https://logo.clearbit.com/tsmc.com", "tags": ["Halbleiter", "Chips", "Tech"], "watchlist": false},
    {"symbol": "SAP.DE", "name": "SAP", "logoUrl": "https://logo.clearbit.com/sap.com", "tags": ["ERP-Software", "Cloud", "B2B"], "watchlist": false},
    {"symbol": "ORCL", "name": "Oracle", "logoUrl": "https://logo.clearbit.com/oracle.com", "tags": ["Datenbanken", "Cloud", "Infrastruktur"], "watchlist": false},
    {"symbol": "AVGO", "name": "Broadcom", "logoUrl": "https://logo.clearbit.com/broadcom.com", "tags": ["Chips", "Netzwerk", "Software"], "watchlist": false},
    {"symbol": "ASML", "name": "ASML", "logoUrl": "https://logo.clearbit.com/asml.com", "tags": ["Lithographie", "Tech", "Halbleiter"], "watchlist": false},
    {"symbol": "GOOGL", "name": "Alphabet", "logoUrl": "https://logo.clearbit.com/google.com", "tags": ["Suche", "Werbung", "KI"], "watchlist": false},
    {"symbol": "QCOM", "name": "Qualcomm", "logoUrl": "https://logo.clearbit.com/qualcomm.com", "tags": ["Mobilfunk", "Prozessoren", "5G"], "watchlist": false},
    {"symbol": "NOW", "name": "ServiceNow", "logoUrl": "https://logo.clearbit.com/servicenow.com", "tags": ["Workflow", "Cloud", "SaaS"], "watchlist": false},
    {"symbol": "INTU", "name": "Intuit", "logoUrl": "https://logo.clearbit.com/intuit.com", "tags": ["Finanzsoftware", "Steuern", "KMU"], "watchlist": false},
    {"symbol": "JPM", "name": "JPMorgan Chase", "logoUrl": "https://logo.clearbit.com/jpmorganchase.com", "tags": ["Großbank", "Finanzen", "Investment"], "watchlist": false},
    {"symbol": "HSBA.L", "name": "HSBC", "logoUrl": "https://logo.clearbit.com/hsbc.com", "tags": ["Banken", "Asien-Fokus", "Vermögen"], "watchlist": false},
    {"symbol": "SAN.PA", "name": "Sanofi", "logoUrl": "https://logo.clearbit.com/sanofi.com", "tags": ["Pharma", "Impfstoffe", "Gesundheit"], "watchlist": false},
    {"symbol": "BLK", "name": "BlackRock", "logoUrl": "https://logo.clearbit.com/blackrock.com", "tags": ["iShares", "Asset Management", "Finanzen"], "watchlist": false},
    {"symbol": "ALV.DE", "name": "Allianz", "logoUrl": "https://logo.clearbit.com/allianz.com", "tags": ["Versicherung", "Vorsorge", "Finanzen"], "watchlist": false},
    {"symbol": "MUV2.DE", "name": "Munich Re", "logoUrl": "https://logo.clearbit.com/munichre.com", "tags": ["Rückversicherung", "Risiko", "Finanzen"], "watchlist": false},
    {"symbol": "SIE.DE", "name": "Siemens", "logoUrl": "https://logo.clearbit.com/siemens.com", "tags": ["Industrie", "Digitalisierung", "Infrastruktur"], "watchlist": false},
    {"symbol": "SU.PA", "name": "Schneider Electric", "logoUrl": "https://logo.clearbit.com/se.com", "tags": ["Energiemanagement", "Automatisierung", "Tech"], "watchlist": false},
    {"symbol": "HON", "name": "Honeywell", "logoUrl": "https://logo.clearbit.com/honeywell.com", "tags": ["Mischkonzern", "Luftfahrt", "Industrie"], "watchlist": false},
    {"symbol": "CAT", "name": "Caterpillar", "logoUrl": "https://logo.clearbit.com/caterpillar.com", "tags": ["Baumaschinen", "Bergbau", "Schwerindustrie"], "watchlist": false},
    {"symbol": "DE", "name": "John Deere", "logoUrl": "https://logo.clearbit.com/deere.com", "tags": ["Agrartechnik", "Forstwirtschaft", "Maschinen"], "watchlist": false},
    {"symbol": "ABBN.SW", "name": "ABB", "logoUrl": "https://logo.clearbit.com/abb.com", "tags": ["Robotik", "Automation", "Stromnetz"], "watchlist": false},
    {"symbol": "6861.T", "name": "Keyence", "logoUrl": "https://logo.clearbit.com/keyence.com", "tags": ["Sensoren", "Mikroskope", "Automation"], "watchlist": false},
    {"symbol": "DG.PA", "name": "Vinci", "logoUrl": "https://logo.clearbit.com/vinci.com", "tags": ["Konzessionen", "Bau", "Infrastruktur"], "watchlist": false},
    {"symbol": "PH", "name": "Parker-Hannifin", "logoUrl": "https://logo.clearbit.com/parker.com", "tags": ["Antriebstechnik", "Luftfahrt", "Maschinenbau"], "watchlist": false},
    {"symbol": "RIO", "name": "Rio Tinto", "logoUrl": "https://logo.clearbit.com/riotinto.com", "tags": ["Bergbau", "Eisenerz", "Rohstoffe"], "watchlist": false},
    {"symbol": "LIN", "name": "Linde", "logoUrl": "https://logo.clearbit.com/linde.com", "tags": ["Gase", "Industrie", "Wasserstoff"], "watchlist": false},
    {"symbol": "AI.PA", "name": "Air Liquide", "logoUrl": "https://logo.clearbit.com/airliquide.com", "tags": ["Industriegase", "Medizin", "Tech"], "watchlist": false},
    {"symbol": "MC.PA", "name": "LVMH", "logoUrl": "https://logo.clearbit.com/lvmh.com", "tags": ["Luxusgüter", "Mode", "Champagner"], "watchlist": false},
    {"symbol": "TTE", "name": "TotalEnergies", "logoUrl": "https://logo.clearbit.com/totalenergies.com", "tags": ["Öl & Gas", "Solar", "Energie"], "watchlist": false},
    {"symbol": "NEE", "name": "NextEra Energy", "logoUrl": "https://logo.clearbit.com/nexteraenergy.com", "tags": ["Grüne Energie", "Versorger", "Windkraft"], "watchlist": false},
    {"symbol": "ORSTED.CO", "name": "Ørsted", "logoUrl": "https://logo.clearbit.com/orsted.com", "tags": ["Offshore-Wind", "Energie", "Nachhaltig"], "watchlist": false},
    {"symbol": "VIE.PA", "name": "Veolia", "logoUrl": "https://logo.clearbit.com/veolia.com", "tags": ["Wasser", "Recycling", "Versorger"], "watchlist": false},
    {"symbol": "IBE.MC", "name": "Iberdrola", "logoUrl": "https://logo.clearbit.com/iberdrola.com", "tags": ["Stromversorger", "Erneuerbare", "Netze"], "watchlist": false},
    {"symbol": "LLY", "name": "Eli Lilly", "logoUrl": "https://logo.clearbit.com/lilly.com", "tags": ["Pharma", "Adipositas", "Biotech"], "watchlist": false},
    {"symbol": "ROG.SW", "name": "Roche", "logoUrl": "https://logo.clearbit.com/roche.com", "tags": ["Pharma", "Diagnostik", "Krebsmedizin"], "watchlist": false},
    {"symbol": "NOVN.SW", "name": "Novartis", "logoUrl": "https://logo.clearbit.com/novartis.com", "tags": ["Generika", "Pharma", "Forschung"], "watchlist": false},
    {"symbol": "ABBV", "name": "AbbVie", "logoUrl": "https://logo.clearbit.com/abbvie.com", "tags": ["Biopharmaka", "Immunologie", "Pharma"], "watchlist": false},
    {"symbol": "JNJ", "name": "Johnson & Johnson", "logoUrl": "https://logo.clearbit.com/jnj.com", "tags": ["Medizintechnik", "Pharma", "Gesundheit"], "watchlist": false},
    {"symbol": "AMZN", "name": "Amazon", "logoUrl": "https://logo.clearbit.com/amazon.com", "tags": ["E-Commerce", "AWS-Cloud", "Logistik"], "watchlist": false},
    {"symbol": "PG", "name": "Procter & Gamble", "logoUrl": "https://logo.clearbit.com/pg.com", "tags": ["Konsumgüter", "Hygiene", "Marken"], "watchlist": false},
    {"symbol": "NESN.SW", "name": "Nestlé", "logoUrl": "https://logo.clearbit.com/nestle.com", "tags": ["Lebensmittel", "Kaffee", "Tiernahrung"], "watchlist": false},
    {"symbol": "MDLZ", "name": "Mondelez", "logoUrl": "https://logo.clearbit.com/mondelezinternational.com", "tags": ["Snacks", "Schokolade", "Kekse"], "watchlist": false},
    {"symbol": "KO", "name": "Coca-Cola", "logoUrl": "https://logo.clearbit.com/coca-colacompany.com", "tags": ["Erfrischungsgetränke", "Marken", "Global"], "watchlist": false},
    {"symbol": "MCD", "name": "McDonald's", "logoUrl": "https://logo.clearbit.com/mcdonalds.com", "tags": ["Fast-Food", "Franchise", "Immobilien"], "watchlist": false},
    {"symbol": "WMT", "name": "Walmart", "logoUrl": "https://logo.clearbit.com/walmart.com", "tags": ["Einzelhandel", "Supermärkte", "USA"], "watchlist": false},
    {"symbol": "FPE3.DE", "name": "Fuchs SE", "logoUrl": "https://logo.clearbit.com/fuchs.com", "tags": ["Schmierstoffe", "Chemie", "Spezialöle"], "watchlist": false},
    {"symbol": "PLD", "name": "Prologis", "logoUrl": "https://logo.clearbit.com/prologis.com", "tags": ["Logistik-Immobilien", "REIT", "Lager"], "watchlist": false},
    {"symbol": "KRN.DE", "name": "Krones", "logoUrl": "https://logo.clearbit.com/krones.com", "tags": ["Verpackungsmaschinen", "Abfüllung", "Industrie"], "watchlist": false},
    {"symbol": "MMK.VI", "name": "Mayr-Melnhof Karton", "logoUrl": "https://logo.clearbit.com/mm-karton.com", "tags": ["Karton", "Verpackung", "Recycling"], "watchlist": false},
    {"symbol": "IBN", "name": "ICICI Bank", "logoUrl": "https://logo.clearbit.com/icicibank.com", "tags": ["Banken", "Indien", "Finanzdienstleistung"], "watchlist": false},
    {"symbol": "1398.HK", "name": "Industrial & Commercial Bank of China", "logoUrl": "https://logo.clearbit.com/icbc.com.cn", "tags": ["Banken", "China", "Staatskonzern"], "watchlist": true},
    {"symbol": "TPE.WA", "name": "Tauron Polska Energia", "logoUrl": "https://logo.clearbit.com/tauron.pl", "tags": ["Energie", "Versorger", "Polen"], "watchlist": true},
    {"symbol": "DNP.WA", "name": "Dino Polska", "logoUrl": "https://logo.clearbit.com/grupadino.pl", "tags": ["Supermärkte", "Einzelhandel", "Polen"], "watchlist": true},
    {"symbol": "LHA.DE", "name": "Deutsche Lufthansa", "logoUrl": "https://logo.clearbit.com/lufthansagroup.com", "tags": ["Airlines", "Luftfahrt", "Logistik"], "watchlist": true},
    {"symbol": "FIH-U.TO", "name": "Fairfax India", "logoUrl": "https://logo.clearbit.com/fairfaxindia.ca", "tags": ["Beteiligungen", "Indien", "Investment"], "watchlist": true},
    {"symbol": "EOAN.DE", "name": "E.ON", "logoUrl": "https://logo.clearbit.com/eon.com", "tags": ["Energienetze", "Infrastruktur", "Versorger"], "watchlist": true},
    {"symbol": "CMCSA", "name": "Comcast A", "logoUrl": "https://logo.clearbit.com/comcastcorporation.com", "tags": ["Medien", "Kabelnetz", "Streaming"], "watchlist": true},
    {"symbol": "KHC", "name": "Kraft Heinz", "logoUrl": "https://logo.clearbit.com/kraftheinzcompany.com", "tags": ["Lebensmittel", "Ketchup", "Marken"], "watchlist": true},
    {"symbol": "VNA.DE", "name": "Vonovia", "logoUrl": "https://logo.clearbit.com/vonovia.de", "tags": ["Immobilien", "Wohnungen", "Vermieter"], "watchlist": true},
    {"symbol": "PKO.WA", "name": "Powszechna Kasa Oszczednosci Bank", "logoUrl": "https://logo.clearbit.com/pkobp.pl", "tags": ["Banken", "Polen", "Finanzen"], "watchlist": true},
    {"symbol": "DNB.OL", "name": "DNB Bank", "logoUrl": "https://logo.clearbit.com/dnb.no", "tags": ["Banken", "Norwegen", "Finanzservice"], "watchlist": true},
    {"symbol": "6506.T", "name": "Yaskawa Electric", "logoUrl": "https://logo.clearbit.com/yaskawa-global.com", "tags": ["Robotik", "Motoren", "Automation"], "watchlist": true},
    {"symbol": "6954.T", "name": "Fanuc", "logoUrl": "https://logo.clearbit.com/fanuc.co.jp", "tags": ["CNC-Systeme", "Roboter", "Fabrikautomation"], "watchlist": true},
    {"symbol": "YAR.OL", "name": "Yara Intl.", "logoUrl": "https://logo.clearbit.com/yara.com", "tags": ["Düngemittel", "Agrar-Chemie", "Ernte"], "watchlist": true},
    {"symbol": "VZ", "name": "Verizon", "logoUrl": "https://logo.clearbit.com/verizon.com", "tags": ["Telekom", "Mobilfunk", "5G"], "watchlist": true},
    {"symbol": "DHL.DE", "name": "DHL", "logoUrl": "https://logo.clearbit.com/dhl.com", "tags": ["Logistik", "Pakete", "Post"], "watchlist": true},
    {"symbol": "EVD.DE", "name": "CTS Eventim", "logoUrl": "https://logo.clearbit.com/eventim.de", "tags": ["Ticketing", "Konzerte", "Live-Events"], "watchlist": true},
    {"symbol": "VER.VI", "name": "Verbund AG", "logoUrl": "https://logo.clearbit.com/verbund.com", "tags": ["Wasserkraft", "Strom", "Österreich"], "watchlist": true},
    {"symbol": "CGNX", "name": "Cognex", "logoUrl": "https://logo.clearbit.com/cognex.com", "tags": ["Bildverarbeitung", "Sensoren", "Tech"], "watchlist": true},
    {"symbol": "EUK3.DE", "name": "EUROKAI Vz.", "logoUrl": "https://logo.clearbit.com/eurokai.de", "tags": ["Hafenterminals", "Logistik", "Schifffahrt"], "watchlist": true},
    {"symbol": "BMW3.DE", "name": "BMW Vz.", "logoUrl": "https://logo.clearbit.com/bmwgroup.com", "tags": ["Automobile", "Premium", "Motorrad"], "watchlist": true},
    {"symbol": "PDD", "name": "Pinduoduo ADR", "logoUrl": "https://logo.clearbit.com/pddholdings.com", "tags": ["E-Commerce", "Temu", "China"], "watchlist": true},
    {"symbol": "BEI.DE", "name": "Beiersdorf", "logoUrl": "https://logo.clearbit.com/beiersdorf.de", "tags": ["Nivea", "Hautpflege", "Konsumgüter"], "watchlist": true},
    {"symbol": "SIX2.DE", "name": "Sixt St.", "logoUrl": "https://logo.clearbit.com/sixt.de", "tags": ["Autovermietung", "Mobilität", "Leasing"], "watchlist": true},
    {"symbol": "ABBN.SW", "name": "ABB (Watchlist)", "logoUrl": "https://logo.clearbit.com/abb.com", "tags": ["Elektrotechnik", "Automation", "Tech"], "watchlist": true},
    {"symbol": "STR.VI", "name": "Strabag", "logoUrl": "https://logo.clearbit.com/strabag.com", "tags": ["Baukonzern", "Infrastruktur", "Tiefbau"], "watchlist": true},
    {"symbol": "FRM.DE", "name": "FRoSTA", "logoUrl": "https://logo.clearbit.com/frosta-ag.de", "tags": ["Tiefkühlkost", "Ernährung", "Lebensmittel"], "watchlist": true},
    {"symbol": "6367.T", "name": "Daikin Industries", "logoUrl": "https://logo.clearbit.com/daikin.com", "tags": ["Klimaanlagen", "Wärmepumpen", "Heizung"], "watchlist": true},
    {"symbol": "ADSK", "name": "Autodesk", "logoUrl": "https://logo.clearbit.com/autodesk.com", "tags": ["CAD-Software", "3D-Design", "Architektur"], "watchlist": true},
    {"symbol": "ADBE", "name": "Adobe", "logoUrl": "https://logo.clearbit.com/adobe.com", "tags": ["Photoshop", "Kreativ-Cloud", "Software"], "watchlist": true},
    {"symbol": "SIKA.SW", "name": "Sika", "logoUrl": "https://logo.clearbit.com/sika.com", "tags": ["Spezialchemie", "Baustoffe", "Klebstoffe"], "watchlist": true},
    {"symbol": "TER", "name": "Teradyne", "logoUrl": "https://logo.clearbit.com/teradyne.com", "tags": ["Testsysteme", "Halbleiter", "Automatisierung"], "watchlist": true},
    {"symbol": "ROK", "name": "Rockwell Automation", "logoUrl": "https://logo.clearbit.com/rockwellautomation.com", "tags": ["Fabrikautomation", "Industriesoftware", "Tech"], "watchlist": true}
]
